{
  "ComponentIndexes": {},
  "ControlUniqueGuids": {},
  "ControlUniqueIds": {
    "App": 1,
    "Atașări_DataCard1": 43,
    "Atașări_DataCard2": 17,
    "Button1": 56,
    "Button1_1": 57,
    "Button2": 55,
    "DataCardKey1": 40,
    "DataCardKey2": 45,
    "DataCardKey3": 14,
    "DataCardKey4": 19,
    "DataCardValue1": 15,
    "DataCardValue2": 20,
    "ErrorMessage1": 42,
    "ErrorMessage2": 47,
    "ErrorMessage3": 16,
    "ErrorMessage4": 21,
    "f_primitc": 46,
    "f_primitnume": 41,
    "fisierele": 22,
    "Form1": 37,
    "Form2": 11,
    "g_excel": 29,
    "galleryTemplate1": 23,
    "galleryTemplate2": 30,
    "Group1": 58,
    "Host": 3,
    "Icon1": 9,
    "Icon2": 25,
    "Icon3": 33,
    "Icon4": 50,
    "Image3": 62,
    "Label1": 51,
    "Label2": 6,
    "Label3": 48,
    "Label4": 7,
    "Label6": 53,
    "Label7": 8,
    "Label8": 10,
    "Label9": 61,
    "NextArrow2": 26,
    "NextArrow3": 32,
    "nume_fisier_1": 54,
    "NumeF": 52,
    "Rectangle2": 24,
    "Rectangle3": 31,
    "Rectangle4": 49,
    "Screen1": 4,
    "Screen2": 59,
    "Separator2": 28,
    "Separator3": 35,
    "Star2": 5,
    "StarVisible1": 39,
    "StarVisible2": 44,
    "StarVisible3": 13,
    "StarVisible4": 18,
    "Timer2": 60,
    "Title2": 27,
    "Title3": 34,
    "Titlu_DataCard1": 12,
    "top": 38,
    "txtEmail": 36
  },
  "FunctionParamsInvariantScripts": {},
  "FunctionParamsInvariantScriptsOnInstances": {},
  "HeaderLastSavedDateTimeUTC": "11/23/2023 12:29:11",
  "IsLegacyComponentAllowGlobalScopeCase": false,
  "LocalConnectionIDReferences": {
    "20cc2073-7e31-434c-9a6d-b6744bc8f2e2": "\"/providers/microsoft.powerapps/apis/shared_logicflows/connections/9600d03f778c43e7bb77cdeb9832205d-9274a944778e0d23\"",
    "85bc1538-26c6-4c02-8803-bcf8639bffc4": "\"/providers/microsoft.powerapps/apis/shared_logicflows/connections/b5bd56d75b09471b96d0e033e1139a27-9274a944778e0d23\"",
    "c67fc714-f26f-4271-a900-ad1cb5976639": "\"/providers/microsoft.powerapps/apis/shared_sharepointonline/connections/51edc5b147af4398818436c4b3b0e714\"",
    "f1b6f3b5-f907-4d5f-b740-5dbf8b9b9b4b": "\"/providers/microsoft.powerapps/apis/shared_office365/connections/shared-office365-90b18e3f-b105-4d29-81bc-ef18a8cb557d\""
  },
  "LocalDatabaseReferencesAsEmpty": false,
  "LocalResourceFileNames": {
    "giphy": "39e92a2b-4da2-42e8-b183-c32d542da813.gif"
  },
  "LocalResourceRootPaths": {
    "giphy": "https://docserverpwaprodweu.blob.core.windows.net/f6634dd4-7270-44cc-a7e1-a79e71573e19-1/resource/Assets0Images039e92a2b-4da2-42e8-b183-c32d542da813.gif?skoid=58690ece-ec83-4ce2-9ce8-883d4d6a54ee&sktid=975f013f-7f24-47e8-a7d3-abc4752bf346&skt=2023-11-23T12%3A15%3A11Z&ske=2023-11-24T12%3A30%3A11Z&sks=b&skv=2021-12-02&sv=2021-12-02&spr=https&se=2023-11-24T12%3A30%3A11Z&sr=b&sp=r&sig=S1rpMIm3d3h69KgjI2JRhE%2BwIheHB8i15jSTX%2Bp8hU4%3D"
  },
  "OrderComponentMetadata": {},
  "OrderComponentTemplate": {},
  "OrderDataSource": {
    "C_excel": 2,
    "C_excel_editat": 6,
    "colFisiere": 7,
    "Convertor": 3,
    "Convertor editat": 4,
    "CustomGallerySample": 5,
    "Office365Outlook": 1,
    "UpConvert": 0
  },
  "OrderGroupControls": {
    "Group1": {
      "Icon4": 0,
      "Label1": 1,
      "Rectangle4": 2
    }
  },
  "OrderPcfTemplate": {},
  "OrderTemplate": {},
  "OrderXMLTemplate": {
    "attachments": 5,
    "button": 8,
    "form": 3,
    "gallery": 6,
    "icon": 2,
    "image": 10,
    "label": 1,
    "rectangle": 7,
    "star": 0,
    "text": 4,
    "timer": 9
  },
  "OverridablePropertiesEntry": {
    "App": {},
    "Atașări_DataCard1": {},
    "Atașări_DataCard2": {},
    "Button1": {},
    "Button1_1": {},
    "Button2": {},
    "DataCardKey1": {},
    "DataCardKey2": {},
    "DataCardKey3": {},
    "DataCardKey4": {},
    "DataCardValue1": {},
    "DataCardValue2": {},
    "ErrorMessage1": {},
    "ErrorMessage2": {},
    "ErrorMessage3": {},
    "ErrorMessage4": {},
    "f_primitc": {},
    "f_primitnume": {},
    "fisierele": {},
    "Form1": {},
    "Form2": {},
    "g_excel": {},
    "galleryTemplate1": {},
    "galleryTemplate2": {},
    "Group1": {},
    "Host": {},
    "Icon1": {},
    "Icon2": {},
    "Icon3": {},
    "Icon4": {},
    "Image3": {},
    "Label1": {},
    "Label2": {},
    "Label3": {},
    "Label4": {},
    "Label6": {},
    "Label7": {},
    "Label8": {},
    "Label9": {},
    "NextArrow2": {},
    "NextArrow3": {},
    "nume_fisier_1": {},
    "NumeF": {},
    "Rectangle2": {},
    "Rectangle3": {},
    "Rectangle4": {},
    "Screen1": {},
    "Screen2": {},
    "Separator2": {},
    "Separator3": {},
    "Star2": {},
    "StarVisible1": {},
    "StarVisible2": {},
    "StarVisible3": {},
    "StarVisible4": {},
    "Timer2": {},
    "Title2": {},
    "Title3": {},
    "Titlu_DataCard1": {},
    "top": {},
    "txtEmail": {}
  },
  "PCFDynamicSchemaForIRRetrievalEntry": {},
  "PCFTemplateEntry": {},
  "PublishOrderIndices": {
    "App": 0,
    "Atașări_DataCard1": 38,
    "Atașări_DataCard2": 12,
    "Button1": 52,
    "Button1_1": 53,
    "Button2": 51,
    "DataCardKey1": 35,
    "DataCardKey2": 40,
    "DataCardKey3": 9,
    "DataCardKey4": 14,
    "DataCardValue1": 10,
    "DataCardValue2": 15,
    "ErrorMessage1": 37,
    "ErrorMessage2": 42,
    "ErrorMessage3": 11,
    "ErrorMessage4": 16,
    "f_primitc": 41,
    "f_primitnume": 36,
    "fisierele": 17,
    "Form1": 32,
    "Form2": 6,
    "g_excel": 24,
    "galleryTemplate1": 18,
    "galleryTemplate2": 25,
    "Group1": 45,
    "Host": 0,
    "Icon1": 4,
    "Icon2": 20,
    "Icon3": 28,
    "Icon4": 46,
    "Image3": 56,
    "Label1": 47,
    "Label2": 1,
    "Label3": 43,
    "Label4": 2,
    "Label6": 49,
    "Label7": 3,
    "Label8": 5,
    "Label9": 55,
    "NextArrow2": 21,
    "NextArrow3": 27,
    "nume_fisier_1": 50,
    "NumeF": 48,
    "Rectangle2": 19,
    "Rectangle3": 26,
    "Rectangle4": 44,
    "Screen1": 0,
    "Screen2": 0,
    "Separator2": 23,
    "Separator3": 30,
    "Star2": 0,
    "StarVisible1": 34,
    "StarVisible2": 39,
    "StarVisible3": 8,
    "StarVisible4": 13,
    "Timer2": 54,
    "Title2": 22,
    "Title3": 29,
    "Titlu_DataCard1": 7,
    "top": 33,
    "txtEmail": 31
  },
  "ResourcesJsonIndices": {
    "Image-giphy": 1,
    "Image-SampleImage": 0,
    "Video-SampleVideo": 2
  },
  "RuleScreenIdWithoutScreen": {},
  "TemplateVersions": {},
  "VolatileProperties": {
    "AnalysisLoadTime": 0.3998753,
    "ControlCount": {
      "attachments": 3,
      "button": 5,
      "form": 2,
      "gallery": 2,
      "galleryTemplate": 2,
      "group": 1,
      "icon": 6,
      "image": 1,
      "label": 24,
      "rectangle": 5,
      "screen": 3,
      "star": 1,
      "text": 4,
      "timer": 1,
      "typedDataCard": 4
    },
    "DeserializationLoadTime": 2.369797
  },
  "WasLocalDatabaseReferencesEmpty": true
}